pybake/__init__.py
pybake/abstractimporter.py
pybake/blobserver.py
pybake/dictfilesystem.py
pybake/dictfilesystembuilder.py
pybake/dictfilesysteminterceptor.py
pybake/errors.py
pybake/exceptions.py
pybake/filesysteminterceptor.py
pybake/launcher.py
pybake/moduletree.py
pybake/pybake.py
pyBake-0.0.2.dist-info/LICENSE
pyBake-0.0.2.dist-info/METADATA
pyBake-0.0.2.dist-info/WHEEL
pyBake-0.0.2.dist-info/top_level.txt
pyBake-0.0.2.dist-info/RECORD
